Metadata-Version: 1.1
Name: ColorPrintX
Version: 0.0.1
Summary: Aviv's way to print with colors ez
Home-page: UNKNOWN
Author: aviv05423
Author-email: avivb60@gmail.com
License: MIT
Keywords: color,print,colorful,printer,prints,bold,underline
Platform: UNKNOWN
Classifier: Development Status :: 5 - Production/Stable
Classifier: Intended Audience :: Education
Classifier: Operating System :: Microsoft :: Windows :: Windows 10
Classifier: License :: OSI Approved :: MIT License
Classifier: Programming Language :: Python :: 3
